instruction_memory.v
module instruction_memory (
    address, data, unvalid_mem_addr
);

parameter ADDR_WIDTH = 16;
parameter DATA_WIDTH = 16;
parameter MEM_DEPTH = 1 << 10;
parameter MEM_OFFSET = 0;


input [ADDR_WIDTH-1:0] address;

output reg [DATA_WIDTH-1:0] data;
output reg unvalid_mem_addr;

wire [15:0] addr;
assign addr = address>>1;

reg  [DATA_WIDTH-1:0] mem [MEM_DEPTH-1:0];

always @* begin
    if((addr >= MEM_OFFSET) && (addr < MEM_OFFSET + MEM_DEPTH)) begin
        data <= mem[addr];
        unvalid_mem_addr <= 0;
    end else begin
        unvalid_mem_addr <= 1;
    end
end
integer i;
initial begin
    
i = 0;
mem[i] = 16'b0011000000001010;
i = i + 1;
mem[i] = 16'b0011000100010100;
i = i + 1;
mem[i] = 16'b0011001011110110;
i = i + 1;
mem[i] = 16'b0011001111101100;
i = i + 1;
mem[i] = 16'b0100001000000000;
i = i + 1;
mem[i] = 16'b0100011101000000;
i = i + 1;
mem[i] = 16'b1101000110000000;
i = i + 1;
mem[i] = 16'b0011111100000000;
i = i + 1;
mem[i] = 16'b1011111011110111;
i = i + 1;

    
end
    
endmodule

memory.v
module memory (
    clk, addr, wr_data, wr_en, rd_data
);

input clk, wr_en;
input [7:0] addr;
input [7:0] wr_data;

output wire [7:0] rd_data;

reg [7:0] zero_page_mem [255:0];

assign rd_data = zero_page_mem[addr];

always @(posedge clk ) begin
    if(wr_en) begin
        if (addr < 16'h100) begin
            zero_page_mem[addr] <= wr_data;
        end
    end
end

endmodule

alu.v
`define and_alu 2'b0000
`define not_alu 2'b0001
`define add_alu 2'b0010

// module test (
    
// );
//     reg [7:0] A,B;
//     reg [2:0] F;
//     wire [7:0] out;
//     wire [3:0] flags;
//     alu al(A, B, F, out, flags);

//     initial begin
//         $dumpfile("alu.vcd");
//         $dumpvars(0,test);
//         A = 8'b10100110;
//         B = 8'b11111111;
//         F = 0;
//         #5
//         F=1;
//         #5
//         F=2;
//         #5
//         $finish;
//     end
    
// endmodule
//010 add
//011 sub
module alu (
    A, B, out, flags, control
);
    input [7:0] A, B;
    input [3:0] control;
    output [7:0] out;
    output [7:0] flags;

    reg[8:0] result;

    assign flags[0] = result[8];            //carry /
    assign flags[1] = result[7:0] == 0;     //zero
    assign flags[2] = A > B;                //is A > B
    assign flags[3] = 0;                    // todo overflow
    assign flags[7:4] = 0;                    //reserved
    assign out = result[7:0];
    
    initial begin
        result = 0;
    end

    always @* begin
        if(control == 3'b010) begin
            result <= A+B;
        end else if (control == 4'b0000) begin
            result <= B;
        end else if (control == 4'b0001) begin // and
            result <= A&B;
        end else if (control == 4'b0011) begin // A-B
            result <= A-B; 
        end else if (control == 4'b0100) begin // or
            result <=A|B;
        end else if (control == 4'b0101) begin // invert
            result <= ~A;
        end else if (control == 4'b0110) begin // shift left
            result <= A << 1;
            result[8] <= A[7];
        end else if (control == 4'b0111) begin //shift right
            result <= A >> 1;
            result[8] <= A[0];
        end else if (control == 4'b1000) begin
            result <= A  < B;
        end
    end
    
endmodule

control.v
`define jmp     4'b0000
`define ld      4'b0001
`define st      4'b0010
`define li      4'b0011
`define add     4'b0100
`define sub     4'b0101
`define and_    4'b0110
`define or_     4'b0111
`define invert  4'b1000
`define lsl     4'b1001
`define lsr     4'b1010
`define beq     4'b1011
`define bne     4'b1100
`define slt     4'b1111

module control (
    instruction, alu_control, regWrite, memWrite,
    regWriteDst, aluBSrcSel, memToReg, branch, aluFlags
);

input [15:0] instruction;
input [7:0] aluFlags;
output reg memWrite, regWrite, regWriteDst, aluBSrcSel, memToReg, branch;
output reg [3:0] alu_control;
wire [3:0] opc;
assign opc = instruction[15:12];

wire aluZeroFlag, aluCarryFlag, aluLargerFlag;

assign aluCarryFlag = aluFlags[0];
assign aluZeroFlag = aluFlags[1];
assign aluLargerFlag = aluFlags[2];

always @* begin
    case (opc)

        `ld: begin
            regWrite <= 1'b1;
            memWrite <= 1'b0;
            alu_control <= 4'b0010;
            regWriteDst <= 1'b1;
            aluBSrcSel <= 1'b0;
            memToReg <= 1'b1;
            branch <= 1'b0;
        end

        `st: begin
            regWrite <= 1'b0;
            memWrite <= 1'b1;
            alu_control <= 4'b0010;
            aluBSrcSel <= 1'b0;
            branch <= 1'b0;
        end

        `li: begin
            regWrite <= 1'b1;
            memWrite <= 1'b0;
            alu_control <= 4'b0000;
            regWriteDst <= 1'b1;
            aluBSrcSel <= 1'b0;
            memToReg <= 1'b0;
            branch <= 1'b0;
        end
        
        `add: begin
            regWrite <= 1'b1;
            memWrite <= 0;
            alu_control <= 4'b0010;
            regWriteDst <= 0;
            aluBSrcSel <= 1;
            memToReg <= 0;
            branch <= 1'b0;
        end

        `sub: begin
            regWrite <= 1'b1;
            memWrite <= 0;
            alu_control <= 4'b0011;
            regWriteDst <= 0;
            aluBSrcSel <= 1;
            memToReg <= 0;
            branch <= 1'b0;            
        end

        `and_: begin
            regWrite <= 1'b1;
            memWrite <= 0;
            alu_control <= 4'b0001;
            regWriteDst <= 0;
            aluBSrcSel <= 1;
            memToReg <= 0;
            branch <= 1'b0;            
        end

        `or_: begin
            regWrite <= 1'b1;
            memWrite <= 0;
            alu_control <= 4'b0100;
            regWriteDst <= 0;
            aluBSrcSel <= 1;
            memToReg <= 0;
            branch <= 1'b0;            
        end

        `invert: begin
            regWrite <= 1'b1;
            memWrite <= 0;
            alu_control <= 4'b0101;
            regWriteDst <= 0;
            aluBSrcSel <= 1;
            memToReg <= 0;
            branch <= 1'b0;            
        end

        `lsl: begin
            regWrite <= 1'b1;
            memWrite <= 0;
            alu_control <= 4'b0110;
            regWriteDst <= 0;
            aluBSrcSel <= 1;
            memToReg <= 0;
            branch <= 1'b0;            
        end

        `lsr: begin
            regWrite <= 1'b1;
            memWrite <= 0;
            alu_control <= 4'b0111;
            regWriteDst <= 0;
            aluBSrcSel <= 1;
            memToReg <= 0;
            branch <= 1'b0;            
        end

        `beq: begin
            regWrite <= 0;
            memWrite <= 0;
            aluBSrcSel <= 1;
            alu_control <= 4'b0011;
            if(aluZeroFlag) begin
                 branch <= 1'b1;
            end else begin
                 branch <= 1'b0;
            end
        end

        `bne: begin
            regWrite <= 0;
            memWrite <= 0;
            aluBSrcSel <= 1;
            alu_control <= 4'b0011;
            if(aluZeroFlag) begin
                 branch <= 1'b0;
            end else begin
                 branch <= 1'b1;
            end
        end

        `jmp: begin
            regWrite <= 0;
            memWrite <= 0;
            branch <= 1'b1;
        end

        `slt: begin
            regWrite <= 1'b1;
            memWrite <= 0;
            alu_control <= 4'b1000;
            regWriteDst <= 0;
            aluBSrcSel <= 1;
            memToReg <= 0;
            branch <= 1'b0;     
        end

        default: begin
            
        end

    endcase
end
    
endmodule

register_files.v
module regfile (
    clk,
    wr_en3, wr_addr3, wr_d3,    
    rd_d2, rd_addr2,
    rd_d1, rd_addr1
);

input clk, wr_en3;  
input[1:0] rd_addr1, rd_addr2, wr_addr3;
input[7:0] wr_d3;
output[7:0] rd_d1, rd_d2;

reg [7:0] registers [3:0]; 


/// work around for iverlog's problem with array dump
wire[7:0] r0, r1, r2, r3;
assign r0 = registers[0];
assign r1 = registers[1];
assign r2 = registers[2];
assign r3 = registers[3];
/// work around for iverlog's problem with array dump

/*
reg[0] A
reg[1] B
reg[2] C
reg[3] SP
*/


// assign rd_d1 = (rd_addr1 != 0) ? registers[rd_addr1] : 0;
// assign rd_d2 = (rd_addr2 != 0) ? registers[rd_addr2] : 0;

assign rd_d1 = registers[rd_addr1];
assign rd_d2 = registers[rd_addr2];

always @(posedge clk ) begin
    if(wr_en3) registers[wr_addr3] <= wr_d3;
end

endmodule

cpu.v
`include "memory.v"
`include "alu.v"
`include "register_files.v"
`include "instruction_memory.v"
`include "control.v"

module cpu (
    rst,
    clk
);
/*
    i type instruction
    op      rs      rt      offset
    15:12   11:10   9:8     7:0

    r type instruction
    op      rs      rt      rd      reserved
    15:12   11:10    9:8     7:6     2:0
*/

input clk, rst;
wire regWrite, memWrite, regWriteDst, aluBSrcSel, memToReg, PCNSource;
wire [3:0] alu_control;
wire [1:0] reg_wr_addr3, reg_rd_addr2, reg_rd_addr1;
wire [7:0] reg_wr_d3, memOut;
wire [7:0] reg_rd_d2, reg_rd_d1, aluBInput;
wire [7:0] offsetSigned, aluResult, branchOffsetSigned, program_counter_n, PCPlus4, PCBranched;
wire [15:0] instruction;
wire [7:0] aluFlags;
reg [15:0] program_counter_c;


regfile register_file(clk, regWrite, reg_wr_addr3, reg_wr_d3, reg_rd_d2, reg_rd_addr2, reg_rd_d1, reg_rd_addr1);

assign reg_rd_addr1 = instruction[11:10];
assign reg_rd_addr2 = instruction[9:8];

assign offsetSigned = (instruction[7] == 0) ? {8'b00000000, instruction[7:0]} : {8'b11111111, instruction[7:0]};

control control_unit(instruction, alu_control, regWrite, memWrite, regWriteDst, aluBSrcSel, memToReg, PCNSource, aluFlags);

alu alu_unit(reg_rd_d1, aluBInput, aluResult, aluFlags, alu_control);
memory mem (clk, aluResult, reg_rd_d2, memWrite, memOut);

instruction_memory instrct_mem(program_counter_c, instruction,);

assign aluBInput = (aluBSrcSel) ? reg_rd_d2 : offsetSigned; // 0 adding offset to A i type
assign reg_wr_d3 = (memToReg) ? memOut : aluResult;                         //
assign reg_wr_addr3 = (regWriteDst) ? instruction[9:8] : instruction[7:6];  // 1 i type 0 r type

assign branchOffsetSigned = {offsetSigned[14:0], 1'b0}; // shift one left
assign PCPlus4 = program_counter_c + 2;
assign PCBranched = branchOffsetSigned + PCPlus4;
assign program_counter_n = (PCNSource) ? PCBranched : PCPlus4;

always @(posedge clk ) begin
    program_counter_c <= program_counter_n;
end

always @(posedge rst ) begin
    if(rst) program_counter_c <= 0;
end

endmodule

cpu_tb.v
`include "cpu.v"
`default_nettype none

module tb_;
reg clk;
reg rst_n;

cpu cp
(
    rst_n, clk
);

localparam CLK_PERIOD = 10;
always #(CLK_PERIOD/2) clk=~clk;

initial begin
    $dumpfile("tb_.vcd");
    $dumpvars(0, tb_);
end

initial begin
    #1 rst_n<=1'bx;clk<=1'bx;
    #(CLK_PERIOD*2) rst_n<=1;
    #(CLK_PERIOD*2) rst_n<=0;clk<=0;
    repeat(20) @(posedge clk);
    rst_n<=1;
    @(posedge clk);
    repeat(10) @(posedge clk);
    $finish(2);
end

endmodule
`default_nettype wire

tb_.vcd
$date
	Sat Jul 30 03:17:34 2022
$end
$version
	Icarus Verilog
$end
$timescale
	1s
$end
$scope module tb_ $end
$var reg 1 ! clk $end
$var reg 1 " rst_n $end
$scope module cp $end
$var wire 1 ! clk $end
$var wire 1 " rst $end
$var wire 8 # reg_wr_d3 [7:0] $end
$var wire 2 $ reg_wr_addr3 [1:0] $end
$var wire 8 % reg_rd_d2 [7:0] $end
$var wire 8 & reg_rd_d1 [7:0] $end
$var wire 2 ' reg_rd_addr2 [1:0] $end
$var wire 2 ( reg_rd_addr1 [1:0] $end
$var wire 1 ) regWriteDst $end
$var wire 1 * regWrite $end
$var wire 8 + program_counter_n [7:0] $end
$var wire 8 , offsetSigned [7:0] $end
$var wire 1 - memWrite $end
$var wire 1 . memToReg $end
$var wire 8 / memOut [7:0] $end
$var wire 16 0 instruction [15:0] $end
$var wire 8 1 branchOffsetSigned [7:0] $end
$var wire 4 2 alu_control [3:0] $end
$var wire 8 3 aluResult [7:0] $end
$var wire 8 4 aluFlags [7:0] $end
$var wire 1 5 aluBSrcSel $end
$var wire 8 6 aluBInput [7:0] $end
$var wire 8 7 PCPlus4 [7:0] $end
$var wire 1 8 PCNSource $end
$var wire 8 9 PCBranched [7:0] $end
$var reg 16 : program_counter_c [15:0] $end
$scope module alu_unit $end
$var wire 8 ; B [7:0] $end
$var wire 8 < out [7:0] $end
$var wire 8 = flags [7:0] $end
$var wire 4 > control [3:0] $end
$var wire 8 ? A [7:0] $end
$var reg 9 @ result [8:0] $end
$upscope $end
$scope module control_unit $end
$var wire 8 A aluFlags [7:0] $end
$var wire 4 B opc [3:0] $end
$var wire 16 C instruction [15:0] $end
$var wire 1 D aluZeroFlag $end
$var wire 1 E aluLargerFlag $end
$var wire 1 F aluCarryFlag $end
$var reg 1 5 aluBSrcSel $end
$var reg 4 G alu_control [3:0] $end
$var reg 1 8 branch $end
$var reg 1 . memToReg $end
$var reg 1 - memWrite $end
$var reg 1 * regWrite $end
$var reg 1 ) regWriteDst $end
$upscope $end
$scope module instrct_mem $end
$var wire 16 H address [15:0] $end
$var wire 16 I addr [15:0] $end
$var reg 16 J data [15:0] $end
$var reg 1 K unvalid_mem_addr $end
$var integer 32 L i [31:0] $end
$upscope $end
$scope module mem $end
$var wire 8 M addr [7:0] $end
$var wire 1 ! clk $end
$var wire 8 N rd_data [7:0] $end
$var wire 1 - wr_en $end
$var wire 8 O wr_data [7:0] $end
$upscope $end
$scope module register_file $end
$var wire 1 ! clk $end
$var wire 8 P r0 [7:0] $end
$var wire 8 Q r1 [7:0] $end
$var wire 8 R r2 [7:0] $end
$var wire 8 S r3 [7:0] $end
$var wire 2 T rd_addr1 [1:0] $end
$var wire 2 U rd_addr2 [1:0] $end
$var wire 8 V rd_d1 [7:0] $end
$var wire 8 W rd_d2 [7:0] $end
$var wire 2 X wr_addr3 [1:0] $end
$var wire 8 Y wr_d3 [7:0] $end
$var wire 1 * wr_en3 $end
$upscope $end
$upscope $end
$upscope $end
$enddefinitions $end
#0
$dumpvars
bx Y
bx X
bx W
bx V
bx U
bx T
bx S
bx R
bx Q
bx P
bx O
bx N
b0 M
b1001 L
1K
bx J
b0xxxxxxxxxxxxxxx I
bx H
bx G
0F
xE
1D
bx C
bx B
b0x10 A
b0 @
bx ?
bx >
b0x10 =
b0 <
bx ;
bx :
bx 9
x8
bx 7
bx 6
x5
b0x10 4
b0 3
bx 2
bx0 1
bx 0
bx /
x.
x-
bx ,
bx +
x*
x)
bx (
bx '
bx &
bx %
bx $
bx #
x"
x!
$end
#21
0D
b0x00 4
b0x00 =
b0x00 A
b1010 3
b1010 <
b1010 M
b1010 @
b1010 #
b1010 Y
b1010 6
b1010 ;
08
0.
05
1)
b0 2
b0 >
b0 G
0-
1*
b10 +
b10110 9
b10100 1
b1010 ,
b0 $
b0 X
b11 B
b0 '
b0 U
b0 (
b0 T
0K
b11000000001010 0
b11000000001010 C
b11000000001010 J
b10 7
b0 I
b0 :
b0 H
1"
#41
0!
0"
#45
b10100 #
b10100 Y
b10100 3
b10100 <
b10100 M
b10100 @
b101000 1
b10100 6
b10100 ;
b10100 ,
b1 $
b1 X
b1 '
b1 U
b11000100010100 0
b11000100010100 C
b11000100010100 J
b100 +
0E
b101100 9
b100 7
b1 I
b0 4
b0 =
b0 A
b1010 &
b1010 ?
b1010 V
bx %
bx O
bx W
b1010 P
b10 :
b10 H
1!
#50
0!
#55
b11110110 #
b11110110 Y
b11110110 3
b11110110 <
b11110110 M
b11110110 @
b11101100 1
b11110110 6
b11110110 ;
b11110110 ,
b10 $
b10 X
b10 '
b10 U
b11001011110110 0
b11001011110110 C
b11001011110110 J
b110 +
b11110010 9
b110 7
b10 I
b100 :
b100 H
bx %
bx O
bx W
b10100 Q
1!
#60
0!
#65
b11101100 #
b11101100 Y
b11101100 3
b11101100 <
b11101100 M
b11101100 @
b11011000 1
b11101100 6
b11101100 ;
b11101100 ,
b11 $
b11 X
b11 '
b11 U
b11001111101100 0
b11001111101100 C
b11001111101100 J
b1000 +
b11100000 9
b1000 7
b11 I
bx %
bx O
bx W
b11110110 R
b110 :
b110 H
1!
#70
0!
#75
1F
1D
b0 #
b0 Y
b0 3
b0 <
b0 M
b100000000 @
15
0)
b10 2
b10 >
b10 G
0E
b0 1
b11 4
b11 =
b11 A
b11110110 6
b11110110 ;
b0 ,
b0 $
b0 X
b100 B
b10 '
b10 U
b100001000000000 0
b100001000000000 C
b100001000000000 J
b1010 +
b1010 9
b1010 7
b100 I
b1000 :
b1000 H
b11110110 %
b11110110 O
b11110110 W
b11101100 S
1!
#80
0!
#85
b10000000 1
b1000000 ,
b1 $
b1 X
b11101100 6
b11101100 ;
1F
1D
b0 #
b0 Y
b11101100 %
b11101100 O
b11101100 W
b11 '
b11 U
b1 (
b1 T
b11 4
b11 =
b11 A
b0 3
b0 <
b0 M
b100011101000000 0
b100011101000000 C
b100011101000000 J
b100000000 @
b1100 +
b10001100 9
b1100 7
b101 I
b10100 &
b10100 ?
b10100 V
b0 P
b1010 :
b1010 H
1!
#90
0!
#95
b0 1
b10000000 ,
b10 $
b10 X
b0 6
b0 ;
0F
1D
b0 #
b0 Y
b1101 B
b0 %
b0 O
b0 W
b1 '
b1 U
b0 (
b0 T
b10 4
b10 =
b10 A
b0 3
b0 <
b0 M
b1101000110000000 0
b1101000110000000 C
b1101000110000000 J
b0 @
b1110 +
b1110 9
b1110 7
b110 I
b1100 :
b1100 H
b0 &
b0 ?
b0 V
b0 Q
1!
#100
0!
#105
0F
1D
b0 #
b0 Y
b0 3
b0 <
b0 M
05
1)
b0 2
b0 >
b0 G
b0 @
b0 ,
b11 $
b11 X
b0 6
b0 ;
1E
b11 B
b11101100 %
b11101100 O
b11101100 W
b11 '
b11 U
b110 4
b110 =
b110 A
b11101100 &
b11101100 ?
b11101100 V
b11 (
b11 T
b11111100000000 0
b11111100000000 C
b11111100000000 J
b10000 +
b10000 9
b10000 7
b111 I
b0 R
b1110 :
b1110 H
1!
#110
0!
#115
1D
b0 #
b0 Y
b0 3
b0 <
b0 M
b0 @
18
b11 2
b11 >
b11 G
15
0*
b11101110 1
b0 6
b0 ;
b11110111 ,
b10 $
b10 X
b1011 B
b10 '
b10 U
b1011111011110111 0
b1011111011110111 C
b1011111011110111 J
b0 +
b0 9
b10010 7
b1000 I
0E
b10000 :
b10000 H
b10 4
b10 =
b10 A
b0 &
b0 ?
b0 V
b0 %
b0 O
b0 W
b0 S
1!
#120
0!
#125
0D
b1010 #
b1010 Y
b0 4
b0 =
b0 A
b1010 3
b1010 <
b1010 M
b1010 @
b1010 6
b1010 ;
08
05
b0 2
b0 >
b0 G
1*
b10100 1
b1010 ,
b0 $
b0 X
b11 B
b0 '
b0 U
b0 (
b0 T
b11000000001010 0
b11000000001010 C
b11000000001010 J
b10 +
b10110 9
b10 7
b0 I
b0 :
b0 H
1!
#130
0!
#135
b10100 #
b10100 Y
b10100 3
b10100 <
b10100 M
b10100 @
b101000 1
b10100 6
b10100 ;
b10100 ,
b1 $
b1 X
b1 '
b1 U
b11000100010100 0
b11000100010100 C
b11000100010100 J
b100 +
b101100 9
b100 7
b1 I
b10 :
b10 H
b1010 &
b1010 ?
b1010 V
b0 %
b0 O
b0 W
b1010 P
1!
#140
0!
#145
b11110110 #
b11110110 Y
b11110110 3
b11110110 <
b11110110 M
b11110110 @
b11101100 1
b11110110 6
b11110110 ;
b11110110 ,
b10 $
b10 X
b10 '
b10 U
b11001011110110 0
b11001011110110 C
b11001011110110 J
b110 +
b11110010 9
b110 7
b10 I
b0 %
b0 O
b0 W
b10100 Q
b100 :
b100 H
1!
#150
0!
#155
b11101100 #
b11101100 Y
b11101100 3
b11101100 <
b11101100 M
b11101100 @
b11011000 1
b11101100 6
b11101100 ;
b11101100 ,
b11 $
b11 X
b11 '
b11 U
b11001111101100 0
b11001111101100 C
b11001111101100 J
b1000 +
b11100000 9
b1000 7
b11 I
b110 :
b110 H
b0 %
b0 O
b0 W
b11110110 R
1!
#160
0!
#165
1F
1D
b0 #
b0 Y
b0 3
b0 <
b0 M
b100000000 @
15
0)
b10 2
b10 >
b10 G
0E
b0 1
b11 4
b11 =
b11 A
b11110110 6
b11110110 ;
b0 ,
b0 $
b0 X
b100 B
b10 '
b10 U
b100001000000000 0
b100001000000000 C
b100001000000000 J
b1010 +
b1010 9
b1010 7
b100 I
b11110110 %
b11110110 O
b11110110 W
b11101100 S
b1000 :
b1000 H
1!
#170
0!
#175
b10000000 1
b1000000 ,
b1 $
b1 X
b11101100 6
b11101100 ;
1F
1D
b0 #
b0 Y
b11101100 %
b11101100 O
b11101100 W
b11 '
b11 U
b1 (
b1 T
b11 4
b11 =
b11 A
b0 3
b0 <
b0 M
b100011101000000 0
b100011101000000 C
b100011101000000 J
b100000000 @
b1100 +
b10001100 9
b1100 7
b101 I
b1010 :
b1010 H
b10100 &
b10100 ?
b10100 V
b0 P
1!
#180
0!
#185
b0 1
b10000000 ,
b10 $
b10 X
b0 6
b0 ;
0F
1D
b0 #
b0 Y
b1101 B
b0 %
b0 O
b0 W
b1 '
b1 U
b0 (
b0 T
b10 4
b10 =
b10 A
b0 3
b0 <
b0 M
b1101000110000000 0
b1101000110000000 C
b1101000110000000 J
b0 @
b1110 +
b1110 9
b1110 7
b110 I
b0 &
b0 ?
b0 V
b0 Q
b1100 :
b1100 H
1!
#190
0!
#195
0F
1D
b0 #
b0 Y
b0 3
b0 <
b0 M
05
1)
b0 2
b0 >
b0 G
b0 @
b0 ,
b11 $
b11 X
b0 6
b0 ;
1E
b11 B
b11101100 %
b11101100 O
b11101100 W
b11 '
b11 U
b110 4
b110 =
b110 A
b11101100 &
b11101100 ?
b11101100 V
b11 (
b11 T
b11111100000000 0
b11111100000000 C
b11111100000000 J
b10000 +
b10000 9
b10000 7
b111 I
b1110 :
b1110 H
b0 R
1!
#200
0!
#205
1D
b0 #
b0 Y
b0 3
b0 <
b0 M
b0 @
18
b11 2
b11 >
b11 G
15
0*
b11101110 1
b0 6
b0 ;
b11110111 ,
b10 $
b10 X
b1011 B
b10 '
b10 U
b1011111011110111 0
b1011111011110111 C
b1011111011110111 J
b0 +
0E
b0 9
b10010 7
b1000 I
b10 4
b10 =
b10 A
b0 &
b0 ?
b0 V
b0 %
b0 O
b0 W
b0 S
b10000 :
b10000 H
1!
#210
0!
#215
0D
b1010 #
b1010 Y
b0 4
b0 =
b0 A
b1010 3
b1010 <
b1010 M
b1010 @
b1010 6
b1010 ;
08
05
b0 2
b0 >
b0 G
1*
b10100 1
b1010 ,
b0 $
b0 X
b11 B
b0 '
b0 U
b0 (
b0 T
b11000000001010 0
b11000000001010 C
b11000000001010 J
b10 +
b10110 9
b10 7
b0 I
b0 :
b0 H
1!
#220
0!
#225
b10100 #
b10100 Y
b10100 3
b10100 <
b10100 M
b10100 @
b101000 1
b10100 6
b10100 ;
b10100 ,
b1 $
b1 X
b1 '
b1 U
b11000100010100 0
b11000100010100 C
b11000100010100 J
b100 +
b101100 9
b100 7
b1 I
b1010 &
b1010 ?
b1010 V
b0 %
b0 O
b0 W
b1010 P
b10 :
b10 H
1!
#230
0!
#235
b1010 #
b1010 Y
b1010 3
b1010 <
b1010 M
b1010 @
b10100 1
b1010 6
b1010 ;
b1010 ,
b0 $
b0 X
b0 '
b0 U
b11000000001010 0
b11000000001010 C
b11000000001010 J
b10 +
b10110 9
b10 7
b0 I
1"
b0 :
b0 H
b1010 %
b1010 O
b1010 W
b10100 Q
1!
#240
0!
#245
b10100 #
b10100 Y
b10100 3
b10100 <
b10100 M
b10100 @
b101000 1
b10100 6
b10100 ;
b10100 ,
b1 $
b1 X
b10100 %
b10100 O
b10100 W
b1 '
b1 U
b11000100010100 0
b11000100010100 C
b11000100010100 J
b100 +
b101100 9
b100 7
b1 I
b10 :
b10 H
1!
#250
0!
#255
b11110110 #
b11110110 Y
b11110110 3
b11110110 <
b11110110 M
b11110110 @
b11101100 1
b11110110 6
b11110110 ;
b11110110 ,
b10 $
b10 X
b0 %
b0 O
b0 W
b10 '
b10 U
b11001011110110 0
b11001011110110 C
b11001011110110 J
b110 +
b11110010 9
b110 7
b10 I
b100 :
b100 H
1!
#260
0!
#265
b11101100 #
b11101100 Y
b11101100 3
b11101100 <
b11101100 M
b11101100 @
b11011000 1
b11101100 6
b11101100 ;
b11101100 ,
b11 $
b11 X
b11 '
b11 U
b11001111101100 0
b11001111101100 C
b11001111101100 J
b1000 +
b11100000 9
b1000 7
b11 I
b0 %
b0 O
b0 W
b11110110 R
b110 :
b110 H
1!
#270
0!
#275
1F
1D
b0 #
b0 Y
b0 3
b0 <
b0 M
b100000000 @
15
0)
b10 2
b10 >
b10 G
0E
b0 1
b11 4
b11 =
b11 A
b11110110 6
b11110110 ;
b0 ,
b0 $
b0 X
b100 B
b10 '
b10 U
b100001000000000 0
b100001000000000 C
b100001000000000 J
b1010 +
b1010 9
b1010 7
b100 I
b1000 :
b1000 H
b11110110 %
b11110110 O
b11110110 W
b11101100 S
1!
#280
0!
#285
b10000000 1
b1000000 ,
b1 $
b1 X
b11101100 6
b11101100 ;
1F
1D
b0 #
b0 Y
b11101100 %
b11101100 O
b11101100 W
b11 '
b11 U
b1 (
b1 T
b11 4
b11 =
b11 A
b0 3
b0 <
b0 M
b100011101000000 0
b100011101000000 C
b100011101000000 J
b100000000 @
b1100 +
b10001100 9
b1100 7
b101 I
b10100 &
b10100 ?
b10100 V
b0 P
b1010 :
b1010 H
1!
#290
0!
#295
b0 1
b10000000 ,
b10 $
b10 X
b0 6
b0 ;
0F
1D
b0 #
b0 Y
b1101 B
b0 %
b0 O
b0 W
b1 '
b1 U
b0 (
b0 T
b10 4
b10 =
b10 A
b0 3
b0 <
b0 M
b1101000110000000 0
b1101000110000000 C
b1101000110000000 J
b0 @
b1110 +
b1110 9
b1110 7
b110 I
b1100 :
b1100 H
b0 &
b0 ?
b0 V
b0 Q
1!
#300
0!
#305
0F
1D
b0 #
b0 Y
b0 3
b0 <
b0 M
05
1)
b0 2
b0 >
b0 G
b0 @
b0 ,
b11 $
b11 X
b0 6
b0 ;
1E
b11 B
b11101100 %
b11101100 O
b11101100 W
b11 '
b11 U
b110 4
b110 =
b110 A
b11101100 &
b11101100 ?
b11101100 V
b11 (
b11 T
b11111100000000 0
b11111100000000 C
b11111100000000 J
b10000 +
b10000 9
b10000 7
b111 I
b0 R
b1110 :
b1110 H
1!
#310
0!
#315
1D
b0 #
b0 Y
b0 3
b0 <
b0 M
b0 @
18
b11 2
b11 >
b11 G
15
0*
b11101110 1
b0 6
b0 ;
b11110111 ,
b10 $
b10 X
b1011 B
b10 '
b10 U
b1011111011110111 0
b1011111011110111 C
b1011111011110111 J
b0 +
b0 9
b10010 7
b1000 I
0E
b10000 :
b10000 H
b10 4
b10 =
b10 A
b0 &
b0 ?
b0 V
b0 %
b0 O
b0 W
b0 S
1!
#320
0!
#325
0D
b1010 #
b1010 Y
b0 4
b0 =
b0 A
b1010 3
b1010 <
b1010 M
b1010 @
b1010 6
b1010 ;
08
05
b0 2
b0 >
b0 G
1*
b10100 1
b1010 ,
b0 $
b0 X
b11 B
b0 '
b0 U
b0 (
b0 T
b11000000001010 0
b11000000001010 C
b11000000001010 J
b10 +
b10110 9
b10 7
b0 I
b0 :
b0 H
1!
#330
0!
#335
b10100 #
b10100 Y
b10100 3
b10100 <
b10100 M
b10100 @
b101000 1
b10100 6
b10100 ;
b10100 ,
b1 $
b1 X
b1 '
b1 U
b11000100010100 0
b11000100010100 C
b11000100010100 J
b100 +
b101100 9
b100 7
b1 I
b10 :
b10 H
b1010 &
b1010 ?
b1010 V
b0 %
b0 O
b0 W
b1010 P
1!
#340
0!
#345
b11110110 #
b11110110 Y
b11110110 3
b11110110 <
b11110110 M
b11110110 @
b11101100 1
b11110110 6
b11110110 ;
b11110110 ,
b10 $
b10 X
b10 '
b10 U
b11001011110110 0
b11001011110110 C
b11001011110110 J
b110 +
b11110010 9
b110 7
b10 I
b0 %
b0 O
b0 W
b10100 Q
b100 :
b100 H
1!
